flet_asp/__init__.py
flet_asp/action.py
flet_asp/atom.py
flet_asp/selector.py
flet_asp/state.py
flet_asp/utils.py
flet_asp/__pycache__/__init__.cpython-312.pyc
flet_asp/__pycache__/__init__.cpython-313.pyc
flet_asp/__pycache__/action.cpython-312.pyc
flet_asp/__pycache__/action.cpython-313.pyc
flet_asp/__pycache__/atom.cpython-312.pyc
flet_asp/__pycache__/atom.cpython-313.pyc
flet_asp/__pycache__/selector.cpython-312.pyc
flet_asp/__pycache__/selector.cpython-313.pyc
flet_asp/__pycache__/state.cpython-312.pyc
flet_asp/__pycache__/state.cpython-313.pyc
flet_asp/__pycache__/utils.cpython-312.pyc
flet_asp/__pycache__/utils.cpython-313.pyc
flet_asp-0.2.2.dist-info/METADATA
flet_asp-0.2.2.dist-info/WHEEL
flet_asp-0.2.2.dist-info/top_level.txt
flet_asp-0.2.2.dist-info/RECORD
