Metadata-Version: 2.4
Name: flet-asp
Version: 0.2.2
Summary: Flet-ASP – The Flet Atomic State Pattern is a reactive state management library for Flet.
Author-email: brunobrown <brunobrown.86@gmail.com>
License-Expression: MIT
Project-URL: Homepage, https://github.com/brunobrown/flet-asp
Project-URL: Repository, https://github.com/brunobrown/flet-asp
Project-URL: Issues, https://github.com/brunobrown/flet-asp/issues
Classifier: Topic :: Software Development :: Libraries
Classifier: Intended Audience :: Developers
Classifier: Natural Language :: English
Classifier: Operating System :: OS Independent
Classifier: Development Status :: 5 - Production/Stable
Classifier: Programming Language :: Python :: 3
Classifier: Programming Language :: Python :: 3.9
Classifier: Programming Language :: Python :: 3.10
Classifier: Programming Language :: Python :: 3.11
Classifier: Programming Language :: Python :: 3.12
Classifier: Programming Language :: Python :: 3.13
Requires-Python: >=3.9
Requires-Dist: flet>=0.25.2
